kivy_deps/__init__.py
kivy_deps/angle/__init__.py
kivy_deps_angle-0.5.0.data/data/share/angle/bin/d3dcompiler_47.dll
kivy_deps_angle-0.5.0.data/data/share/angle/bin/libEGL.dll
kivy_deps_angle-0.5.0.data/data/share/angle/bin/libGLESv2.dll
kivy_deps_angle-0.5.0.dist-info/METADATA
kivy_deps_angle-0.5.0.dist-info/WHEEL
kivy_deps_angle-0.5.0.dist-info/top_level.txt
kivy_deps_angle-0.5.0.dist-info/RECORD
