Metadata-Version: 2.4
Name: kivy_deps.angle
Version: 0.5.0
Summary: Repackaged binary dependency of Kivy.
Home-page: http://kivy.org/
Author: Kivy Team and other contributors
Author-email: kivy-dev@googlegroups.com
License: MIT
Dynamic: author
Dynamic: author-email
Dynamic: home-page
Dynamic: license
Dynamic: summary
